nlp_architect/__init__.py
nlp_architect/nlp-inference
nlp_architect/nlp-train
nlp_architect/version.py
nlp_architect/api/__init__.py
nlp_architect/api/abstract_api.py
nlp_architect/api/base.py
nlp_architect/api/bist_parser_api.py
nlp_architect/api/intent_extraction_api.py
nlp_architect/api/ner_api.py
nlp_architect/cli/__init__.py
nlp_architect/cli/cmd_registry.py
nlp_architect/common/__init__.py
nlp_architect/common/config.py
nlp_architect/common/core_nlp_doc.py
nlp_architect/common/high_level_doc.py
nlp_architect/common/cdc/__init__.py
nlp_architect/common/cdc/cluster.py
nlp_architect/common/cdc/mention_data.py
nlp_architect/common/cdc/topics.py
nlp_architect/data/__init__.py
nlp_architect/data/conll.py
nlp_architect/data/fasttext_emb.py
nlp_architect/data/glue_tasks.py
nlp_architect/data/intent_datasets.py
nlp_architect/data/ptb.py
nlp_architect/data/sequence_classification.py
nlp_architect/data/sequential_tagging.py
nlp_architect/data/utils.py
nlp_architect/data/cdc_resources/__init__.py
nlp_architect/data/cdc_resources/data_types/__init__.py
nlp_architect/data/cdc_resources/data_types/wiki/__init__.py
nlp_architect/data/cdc_resources/data_types/wiki/wikipedia_page.py
nlp_architect/data/cdc_resources/data_types/wiki/wikipedia_page_extracted_relations.py
nlp_architect/data/cdc_resources/data_types/wiki/wikipedia_pages.py
nlp_architect/data/cdc_resources/data_types/wn/__init__.py
nlp_architect/data/cdc_resources/data_types/wn/wordnet_page.py
nlp_architect/data/cdc_resources/embedding/__init__.py
nlp_architect/data/cdc_resources/embedding/embed_elmo.py
nlp_architect/data/cdc_resources/embedding/embed_glove.py
nlp_architect/data/cdc_resources/gen_scripts/__init__.py
nlp_architect/data/cdc_resources/gen_scripts/create_reference_dict_dump.py
nlp_architect/data/cdc_resources/gen_scripts/create_verbocean_dump.py
nlp_architect/data/cdc_resources/gen_scripts/create_wiki_dump.py
nlp_architect/data/cdc_resources/gen_scripts/create_word_embed_elmo_dump.py
nlp_architect-0.5.4.dist-info/LICENSE
nlp_architect-0.5.4.dist-info/METADATA
nlp_architect-0.5.4.dist-info/WHEEL
nlp_architect-0.5.4.dist-info/top_level.txt
nlp_architect-0.5.4.dist-info/RECORD
