Metadata-Version: 2.1
Name: nlp-architect
Version: 0.5.4
Summary: Intel AI Lab NLP and NLU research model library
Home-page: https://github.com/NervanaSystems/nlp-architect
Author: Intel AI Lab
Author-email: nlp_architect@intel.com
License: Apache 2.0
Keywords: NLP NLU deep learning natural language processing tensorflow pytorch
Platform: UNKNOWN
Classifier: Development Status :: 3 - Alpha
Classifier: Intended Audience :: End Users/Desktop
Classifier: Intended Audience :: Developers
Classifier: Intended Audience :: Science/Research
Classifier: License :: OSI Approved :: Apache Software License
Classifier: Programming Language :: Python :: 3
Classifier: Programming Language :: Python :: 3.6
Classifier: Topic :: Scientific/Engineering
Classifier: Topic :: Scientific/Engineering :: Artificial Intelligence
Classifier: Topic :: Software Development :: Libraries
Classifier: Topic :: Software Development :: Libraries :: Python Modules
Classifier: Topic :: Scientific/Engineering :: Information Analysis
Classifier: Environment :: Console
Classifier: Environment :: Web Environment
Classifier: Operating System :: POSIX
Classifier: Operating System :: MacOS :: MacOS X
Requires-Python: >=3.6.*
Requires-Dist: tensorflow (==1.15.2)
Requires-Dist: dynet (==2.1)
Requires-Dist: torch (==1.4.0)
Requires-Dist: transformers (==2.4.1)
Requires-Dist: spacy (==2.1.8)
Requires-Dist: nltk
Requires-Dist: gensim
Requires-Dist: scikit-learn (==0.20.2)
Requires-Dist: scipy
Requires-Dist: numpy (==1.16.4)
Requires-Dist: seqeval
Requires-Dist: h5py
Requires-Dist: tqdm (==4.35.0)
Requires-Dist: six
Requires-Dist: future
Requires-Dist: requests
Provides-Extra: all
Requires-Dist: tensorflow-hub ; extra == 'all'
Requires-Dist: elasticsearch ; extra == 'all'
Requires-Dist: wordfreq ; extra == 'all'
Requires-Dist: newspaper3k ; extra == 'all'
Requires-Dist: pywikibot ; extra == 'all'
Requires-Dist: num2words ; extra == 'all'
Requires-Dist: bokeh ; extra == 'all'
Requires-Dist: pandas ; extra == 'all'
Requires-Dist: hyperopt ; extra == 'all'
Requires-Dist: termcolor ; extra == 'all'
Provides-Extra: dev
Requires-Dist: sphinx (==1.8.5) ; extra == 'dev'
Requires-Dist: sphinx-rtd-theme ; extra == 'dev'
Requires-Dist: flake8-html ; extra == 'dev'
Requires-Dist: black ; extra == 'dev'
Requires-Dist: pep8 ; extra == 'dev'
Requires-Dist: flake8 ; extra == 'dev'
Requires-Dist: pytest ; extra == 'dev'
Requires-Dist: pytest-cov ; extra == 'dev'
Requires-Dist: pytest-mock ; extra == 'dev'
Requires-Dist: pytest-xdist ; extra == 'dev'
Requires-Dist: pylint ; extra == 'dev'
